mloda/testing/__init__.py
mloda/testing/base.py
mloda_testing-0.2.6.dist-info/METADATA
mloda_testing-0.2.6.dist-info/WHEEL
mloda_testing-0.2.6.dist-info/top_level.txt
mloda_testing-0.2.6.dist-info/RECORD
